avd/__init__.py
avd/common.py
avd/debug.py
avd/fileutils.py
avd/module.py
avd-0.0.1.dist-info/DESCRIPTION.rst
avd-0.0.1.dist-info/METADATA
avd-0.0.1.dist-info/RECORD
avd-0.0.1.dist-info/WHEEL
avd-0.0.1.dist-info/metadata.json
avd-0.0.1.dist-info/top_level.txt
